PFRWebScraper/ScrapePlayerData.py
PFRWebScraper/ScrapeTeamData.py
PFRWebScraper/ScrapeURLs.py
PFRWebScraper/__init__.py
PFRWebScraper/Includes/Configuration.py
PFRWebScraper/Includes/MyOpener.py
PFRWebScraper/Includes/PositionAbstract.py
PFRWebScraper/Includes/ScrapeDataAbstract.py
PFRWebScraper/Includes/__init__.py
PFRWebScraper/Position/__init__.py
PFRWebScraper/Position/DefenseAndFumbles/DefenseAndFumbles.py
PFRWebScraper/Position/DefenseAndFumbles/DefenseAndFumblesPlayoffs.py
PFRWebScraper/Position/DefenseAndFumbles/DefenseAndFumblesRegularSeason.py
PFRWebScraper/Position/DefenseAndFumbles/__init__.py
PFRWebScraper/Position/Kicking/Kicking.py
PFRWebScraper/Position/Kicking/KickingPlayoffs.py
PFRWebScraper/Position/Kicking/KickingRegularSeason.py
PFRWebScraper/Position/Kicking/__init__.py
PFRWebScraper/Position/Passing/Passing.py
PFRWebScraper/Position/Passing/PassingAdjusted.py
PFRWebScraper/Position/Passing/PassingAdvancedAccuracy.py
PFRWebScraper/Position/Passing/PassingAdvancedAirYards.py
PFRWebScraper/Position/Passing/PassingAdvancedPlayType.py
PFRWebScraper/Position/Passing/PassingAdvancedPressure.py
PFRWebScraper/Position/Passing/PassingPlayoffs.py
PFRWebScraper/Position/Passing/PassingRegularSeason.py
PFRWebScraper/Position/Passing/__init__.py
PFRWebScraper/Position/Returns/Returns.py
PFRWebScraper/Position/Returns/ReturnsPlayoffs.py
PFRWebScraper/Position/Returns/ReturnsRegularSeason.py
PFRWebScraper/Position/Returns/__init__.py
PFRWebScraper/Position/RushingReceiving/RushingReceiving.py
PFRWebScraper/Position/RushingReceiving/RushingReceivingAdvanced.py
PFRWebScraper/Position/RushingReceiving/RushingReceivingPlayoffs.py
PFRWebScraper/Position/RushingReceiving/RushingReceivingRegularSeason.py
PFRWebScraper/Position/RushingReceiving/__init__.py
PFRWebScraper/Position/Scoring/Scoring.py
PFRWebScraper/Position/Scoring/ScoringPlayoffs.py
PFRWebScraper/Position/Scoring/ScoringRegularSeason.py
PFRWebScraper/Position/Scoring/__init__.py
PFRWebScraper-1.0.1.dist-info/LICENSE
PFRWebScraper-1.0.1.dist-info/METADATA
PFRWebScraper-1.0.1.dist-info/WHEEL
PFRWebScraper-1.0.1.dist-info/top_level.txt
PFRWebScraper-1.0.1.dist-info/RECORD
